setup.py
src/digimat/__init__.py
src/digimat.cryptedwebservice.egg-info/PKG-INFO
src/digimat.cryptedwebservice.egg-info/SOURCES.txt
src/digimat.cryptedwebservice.egg-info/dependency_links.txt
src/digimat.cryptedwebservice.egg-info/namespace_packages.txt
src/digimat.cryptedwebservice.egg-info/not-zip-safe
src/digimat.cryptedwebservice.egg-info/not-zip-safe (1)
src/digimat.cryptedwebservice.egg-info/requires.txt
src/digimat.cryptedwebservice.egg-info/top_level.txt
src/digimat/cryptedwebservice/__init__.py
src/digimat/cryptedwebservice/cryptedwebservice.py
src/digimat/cryptedwebservice/cwsnotifier.py