Metadata-Version: 1.1
Name: digimat.cryptedwebservice
Version: 0.1.11
Summary: Digimat Generic Crypted Webservice
Home-page: http://www.digimat.ch
Author: Frederic Hess
Author-email: fhess@splust.ch
License: PSF
Platform: UNKNOWN
Classifier: Development Status :: 4 - Beta
Classifier: Programming Language :: Python :: 3
